pyrtshm/__init__.py
pyrtshm/__main__.py
pyrtshm/base.py
pyrtshm/metrics.py
pyrtshm-0.0.3.dist-info/LICENSE
pyrtshm-0.0.3.dist-info/METADATA
pyrtshm-0.0.3.dist-info/WHEEL
pyrtshm-0.0.3.dist-info/entry_points.txt
pyrtshm-0.0.3.dist-info/top_level.txt
pyrtshm-0.0.3.dist-info/RECORD
