Metadata-Version: 2.1
Name: pyrtshm
Version: 0.0.3
Summary: Awesome pyrtshm created by pappacena
Home-page: https://github.com/pappacena/pyrtshm/
Author: pappacena
License: UNKNOWN
Platform: UNKNOWN
License-File: LICENSE
Requires-Dist: protobuf (==3.17.3)
Requires-Dist: types-protobuf (==3.17.4)
Provides-Extra: test
Requires-Dist: pytest ; extra == 'test'
Requires-Dist: coverage ; extra == 'test'
Requires-Dist: flake8 ; extra == 'test'
Requires-Dist: black ; extra == 'test'
Requires-Dist: isort ; extra == 'test'
Requires-Dist: pytest-cov ; extra == 'test'
Requires-Dist: codecov ; extra == 'test'
Requires-Dist: mypy ; extra == 'test'
Requires-Dist: gitchangelog ; extra == 'test'
Requires-Dist: mkdocs ; extra == 'test'
